django_secrets/__init__.py
django_secrets/secrets.py
django_simple_secrets-0.1.0.dist-info/LICENSE
django_simple_secrets-0.1.0.dist-info/METADATA
django_simple_secrets-0.1.0.dist-info/WHEEL
django_simple_secrets-0.1.0.dist-info/top_level.txt
django_simple_secrets-0.1.0.dist-info/RECORD
