Metadata-Version: 2.1
Name: django-simple-secrets
Version: 0.1.0
Summary: A Django integration for AWS Secrets Manager with caching and lazy loading support
Home-page: https://github.com/efficient-solutions/django-simple-secrets
Author: Efficient Solutions LLC
Author-email: contact@efficient.solutions
License: MIT
Keywords: Django,AWS Secrets Manager
Classifier: Intended Audience :: Developers
Classifier: Natural Language :: English
Classifier: License :: OSI Approved :: MIT License
Classifier: Programming Language :: Python
Classifier: Programming Language :: Python :: 3
Classifier: Programming Language :: Python :: 3 :: Only
Classifier: Programming Language :: Python :: 3.10
Classifier: Programming Language :: Python :: 3.11
Classifier: Programming Language :: Python :: 3.12
Requires-Python: >= 3.10
License-File: LICENSE
Requires-Dist: Django <6,>=4
